{
  "iniciado": "2026-06-10T11:25:54.839646",
  "leiloeiros_processados": 9,
  "imoveis_total": 51,
  "imoveis_por_leiloeiro": {
    "Vladmir Oliani": 16,
    "Vera Lucia Aguiar de Sousa": 16,
    "Vera Maria Aguiar de Sousa": 16,
    "Patricia Pimentel Grocoski Costa": 3
  },
  "erros": [
    "Evanilde Aquino Pimentel Rosa: 'charmap' codec can't encode character '\\u2192' in",
    "Francisco Portela Aguiar: 'charmap' codec can't encode character '\\u2192' in",
    "Deonizia Kiratch: 'charmap' codec can't encode character '\\u2192' in",
    "Ana Carolina Zaninetti Rosa: 'charmap' codec can't encode character '\\u2192' in",
    "Marcus Allain de Oliveira Barbosa: 'charmap' codec can't encode character '\\u2192' in",
    "Maria Vanielly de Lima Honorato Portela: sem URL",
    "Alex Willian Hoppe: 'charmap' codec can't encode character '\\u2192' in",
    "Bruno Pimentel Rosa: 'charmap' codec can't encode character '\\u2192' in",
    "Daniel Elias Garcia: 'charmap' codec can't encode character '\\u2192' in",
    "Jonas Gabriel Antunes Moreira: sem URL",
    "Maciel Rodrigues Chaves: sem URL",
    "Fernando Caetano Moreira Filho: 'charmap' codec can't encode character '\\u2192' in",
    "Lucas Rafael Antunes Moreira: 'charmap' codec can't encode character '\\u2192' in",
    "Pedro Augusto da Costa Silva: sem URL",
    "Joabe Balbino da Silva: 'charmap' codec can't encode character '\\u2192' in",
    "Angelica Vilas Boas Nunes: 'charmap' codec can't encode character '\\u2192' in",
    "Thais Costa Bastos Teixeira: 'charmap' codec can't encode character '\\u2192' in",
    "Sandro de Oliveira: 'charmap' codec can't encode character '\\u2192' in",
    "Marcus Vinicius Moreira Chaves: sem URL",
    "Dora Plat: 'charmap' codec can't encode character '\\u2192' in",
    "Wallason Silva Beltrame: 'charmap' codec can't encode character '\\u2192' in",
    "Rodrigo Aparecido Rigolon da Silva: 'charmap' codec can't encode character '\\u2192' in",
    "Antonio Carlos Celso Santos Frazao: 'charmap' codec can't encode character '\\u2192' in",
    "Victor Alberto Severino Frazao: 'charmap' codec can't encode character '\\u2192' in",
    "Jaqueline Vieira de Amorim: 'charmap' codec can't encode character '\\u2192' in",
    "Flavia Correa Duarte Feitosa: sem URL",
    "Michael de Oliveira: sem URL",
    "Icaro Alexandre Felfili Jardim: sem URL",
    "Diogo Reis Dutra: 'charmap' codec can't encode character '\\u2192' in",
    "Carlos Henrique Barbosa: 'charmap' codec can't encode character '\\u2192' in",
    "Maria Rafaela Barbosa Silva: sem URL"
  ],
  "last_report": "2026-06-10T11:27:07.978456",
  "status": "concluido",
  "tempo_total_min": 1.2189602851867676
}